floske/__init__.py
floske/py.typed
floske-0.0.0.dist-info/LICENSE
floske-0.0.0.dist-info/METADATA
floske-0.0.0.dist-info/WHEEL
floske-0.0.0.dist-info/top_level.txt
floske-0.0.0.dist-info/zip-safe
floske-0.0.0.dist-info/RECORD
